{"hcode":"11120","name":"เทพรัตนเวชชานุกูล เฉลิมพระเกียรติ ๖๐ พรรษา","prov":"เชียงใหม่","grp":"รพช.F2 P30,000-60,000","level":"รพช.F2","period":256908,"periodLabel":"พ.ค.69","trend":[{"t":256609,"cr":3.41,"qr":3.22,"cash":2.51,"nwc":49005256.0,"ni":-3116064.0,"ebitda":4858987.0,"reserve":30731072.0,"li":0.0,"st":1.0,"su":0.0,"risk":1.0,"source":"gl"},{"t":256610,"cr":3.07,"qr":2.88,"cash":2.17,"nwc":42805486.0,"ni":-11006960.0,"ebitda":-2124496.0,"reserve":24086607.0,"li":0.0,"st":1.0,"su":0.0,"risk":1.0,"source":"gl"},{"t":256611,"cr":2.88,"qr":2.69,"cash":1.88,"nwc":38082814.0,"ni":-16401649.0,"ebitda":-6601469.0,"reserve":17951814.0,"li":0.0,"st":1.0,"su":0.0,"risk":1.0,"source":"gl"},{"t":256612,"cr":3.11,"qr":2.87,"cash":2.11,"nwc":33898341.0,"ni":-11069541.0,"ebitda":1232664.0,"reserve":17918347.0,"li":0.0,"st":1.0,"su":0.0,"risk":1.0,"source":"gl"},{"t":256701,"cr":3.38,"qr":3.18,"cash":2.52,"nwc":41115960.0,"ni":5215145.0,"ebitda":6434898.0,"reserve":26271933.0,"li":0.0,"st":0.0,"su":0.0,"risk":0.0,"source":"reported"},{"t":256702,"cr":3.36,"qr":3.15,"cash":2.6,"nwc":42881311.0,"ni":6037489.0,"ebitda":8495259.0,"reserve":29017115.0,"li":0.0,"st":0.0,"su":0.0,"risk":0.0,"source":"reported"},{"t":256703,"cr":3.75,"qr":3.57,"cash":2.89,"nwc":54321004.0,"ni":15738380.0,"ebitda":19433706.0,"reserve":37348327.0,"li":0.0,"st":0.0,"su":0.0,"risk":0.0,"source":"reported"},{"t":256704,"cr":3.75,"qr":3.55,"cash":2.95,"nwc":49626005.0,"ni":9475205.0,"ebitda":14394295.0,"reserve":35195131.0,"li":0.0,"st":0.0,"su":0.0,"risk":0.0,"source":"reported"},{"t":256705,"cr":3.34,"qr":3.11,"cash":2.42,"nwc":43597519.0,"ni":2243962.0,"ebitda":8408157.0,"reserve":26466949.0,"li":0.0,"st":0.0,"su":0.0,"risk":0.0,"source":"reported"},{"t":256706,"cr":2.97,"qr":2.74,"cash":2.09,"nwc":39089312.0,"ni":-2240845.0,"ebitda":5178844.0,"reserve":21543748.0,"li":0.0,"st":1.0,"su":0.0,"risk":1.0,"source":"reported"},{"t":256707,"cr":2.91,"qr":2.69,"cash":1.94,"nwc":41068968.0,"ni":-1516793.0,"ebitda":7157576.0,"reserve":20223687.0,"li":0.0,"st":1.0,"su":0.0,"risk":1.0,"source":"reported"},{"t":256708,"cr":3.2,"qr":2.9,"cash":2.0,"nwc":38245417.0,"ni":-3164587.0,"ebitda":4861481.0,"reserve":17394923.0,"li":0.0,"st":1.0,"su":0.0,"risk":1.0,"source":"reported"},{"t":256709,"cr":2.02,"qr":1.82,"cash":1.35,"nwc":29424073.0,"ni":-13984058.0,"ebitda":-3921858.0,"reserve":10122701.0,"li":0.0,"st":1.0,"su":0.0,"risk":1.0,"source":"reported"},{"t":256710,"cr":2.03,"qr":1.9,"cash":1.5,"nwc":34228209.0,"ni":-10355672.0,"ebitda":1034115.0,"reserve":16528106.0,"li":0.0,"st":1.0,"su":0.0,"risk":1.0,"source":"reported"},{"t":256711,"cr":1.81,"qr":1.68,"cash":1.3,"nwc":26175956.0,"ni":-18648303.0,"ebitda":-5895285.0,"reserve":9794861.0,"li":0.0,"st":1.0,"su":0.0,"risk":1.0,"source":"reported"},{"t":256712,"cr":1.62,"qr":1.48,"cash":1.18,"nwc":21507677.0,"ni":-24361319.0,"ebitda":-10249179.0,"reserve":6425570.0,"li":0.0,"st":1.0,"su":0.0,"risk":1.0,"source":"reported"},{"t":256801,"cr":1.94,"qr":1.78,"cash":1.29,"nwc":29757674.0,"ni":6657835.0,"ebitda":8015779.0,"reserve":9047217.0,"li":0.0,"st":0.0,"su":0.0,"risk":0.0,"source":"reported"},{"t":256802,"cr":3.07,"qr":2.84,"cash":2.26,"nwc":43390788.0,"ni":20470051.0,"ebitda":23183284.0,"reserve":25356184.0,"li":0.0,"st":0.0,"su":0.0,"risk":0.0,"source":"reported"},{"t":256803,"cr":3.21,"qr":3.01,"cash":2.48,"nwc":48379616.0,"ni":24679330.0,"ebitda":28744062.0,"reserve":32496389.0,"li":0.0,"st":0.0,"su":0.0,"risk":0.0,"source":"reported"},{"t":256804,"cr":2.92,"qr":2.75,"cash":2.21,"nwc":44528090.0,"ni":20336102.0,"ebitda":25753800.0,"reserve":28029375.0,"li":0.0,"st":0.0,"su":0.0,"risk":0.0,"source":"reported"},{"t":256805,"cr":2.57,"qr":2.42,"cash":2.01,"nwc":49902878.0,"ni":25343028.0,"ebitda":32131058.0,"reserve":32321988.0,"li":0.0,"st":0.0,"su":0.0,"risk":0.0,"source":"reported"},{"t":256806,"cr":2.52,"qr":2.37,"cash":1.9,"nwc":47491803.0,"ni":21994369.0,"ebitda":29864286.0,"reserve":28221436.0,"li":0.0,"st":0.0,"su":0.0,"risk":0.0,"source":"reported"},{"t":256807,"cr":2.62,"qr":2.45,"cash":1.92,"nwc":47060707.0,"ni":23008196.0,"ebitda":32268999.0,"reserve":25021526.0,"li":0.0,"st":0.0,"su":0.0,"risk":0.0,"source":"reported"},{"t":256808,"cr":3.33,"qr":3.12,"cash":2.55,"nwc":52750037.0,"ni":27652758.0,"ebitda":38155972.0,"reserve":35083860.0,"li":0.0,"st":0.0,"su":0.0,"risk":0.0,"source":"reported"},{"t":256809,"cr":3.05,"qr":2.85,"cash":2.37,"nwc":49539124.0,"ni":23209118.0,"ebitda":34944984.0,"reserve":33057100.0,"li":0.0,"st":0.0,"su":0.0,"risk":0.0,"source":"reported"},{"t":256810,"cr":3.02,"qr":2.8,"cash":2.29,"nwc":43102836.0,"ni":17575240.0,"ebitda":28546330.0,"reserve":27389530.0,"li":0.0,"st":0.0,"su":0.0,"risk":0.0,"source":"reported"},{"t":256811,"cr":2.68,"qr":2.46,"cash":1.96,"nwc":40166792.0,"ni":13412357.0,"ebitda":25610096.0,"reserve":22936398.0,"li":0.0,"st":0.0,"su":0.0,"risk":0.0,"source":"reported"},{"t":256812,"cr":3.01,"qr":2.79,"cash":1.89,"nwc":38260742.0,"ni":9782424.0,"ebitda":23225093.0,"reserve":16548317.0,"li":0.0,"st":0.0,"su":0.0,"risk":0.0,"source":"reported"},{"t":256901,"cr":3.35,"qr":3.19,"cash":2.54,"nwc":58624852.0,"ni":20934819.0,"ebitda":22197976.0,"reserve":38423921.0,"li":0.0,"st":0.0,"su":0.0,"risk":0.0,"source":"reported"},{"t":256902,"cr":3.22,"qr":3.04,"cash":2.35,"nwc":56570570.0,"ni":18599158.0,"ebitda":21125311.0,"reserve":33635161.0,"li":0.0,"st":0.0,"su":0.0,"risk":0.0,"source":"reported"},{"t":256903,"cr":4.17,"qr":3.9,"cash":3.15,"nwc":51735343.0,"ni":13777408.0,"ebitda":17566964.0,"reserve":35063474.0,"li":0.0,"st":0.0,"su":0.0,"risk":0.0,"source":"reported"},{"t":256904,"cr":4.24,"qr":3.95,"cash":3.12,"nwc":47410018.0,"ni":8649448.0,"ebitda":13695068.0,"reserve":31058392.0,"li":0.0,"st":0.0,"su":0.0,"risk":0.0,"source":"reported"},{"t":256905,"cr":4.03,"qr":3.78,"cash":3.0,"nwc":52358194.0,"ni":14341618.0,"ebitda":20701254.0,"reserve":34501903.0,"li":0.0,"st":0.0,"su":0.0,"risk":0.0,"source":"gl"},{"t":256906,"cr":3.61,"qr":3.39,"cash":2.82,"nwc":57491722.0,"ni":20299195.0,"ebitda":27948033.0,"reserve":40198905.0,"li":0.0,"st":0.0,"su":0.0,"risk":0.0,"source":"reported"},{"t":256907,"cr":3.23,"qr":3.0,"cash":2.51,"nwc":52696093.0,"ni":15255969.0,"ebitda":24166489.0,"reserve":35808722.0,"li":0.0,"st":0.0,"su":0.0,"risk":0.0,"source":"reported"},{"t":256908,"cr":3.43,"qr":3.15,"cash":2.55,"nwc":52021080.0,"ni":15375592.0,"ebitda":25510747.0,"reserve":32837370.0,"li":0.0,"st":0.0,"su":0.0,"risk":0.0,"source":"reported"}],"peer":{"grp":[{"t":256609,"cr_p25":2.07,"cr_med":2.67,"cr_p75":3.83,"qr_p25":1.91,"qr_med":2.51,"qr_p75":3.58,"cash_p25":1.51,"cash_med":1.91,"cash_p75":3.13},{"t":256610,"cr_p25":1.96,"cr_med":2.44,"cr_p75":3.54,"qr_p25":1.81,"qr_med":2.29,"qr_p75":3.29,"cash_p25":1.3,"cash_med":1.64,"cash_p75":2.56},{"t":256611,"cr_p25":1.84,"cr_med":2.43,"cr_p75":3.59,"qr_p25":1.71,"qr_med":2.24,"qr_p75":3.29,"cash_p25":1.03,"cash_med":1.43,"cash_p75":2.48},{"t":256612,"cr_p25":1.66,"cr_med":2.23,"cr_p75":4.02,"qr_p25":1.53,"qr_med":2.03,"qr_p75":3.6,"cash_p25":0.94,"cash_med":1.38,"cash_p75":2.48},{"t":256701,"cr_p25":1.87,"cr_med":2.51,"cr_p75":3.58,"qr_p25":1.77,"qr_med":2.38,"qr_p75":3.38,"cash_p25":1.19,"cash_med":1.61,"cash_p75":2.62},{"t":256702,"cr_p25":1.75,"cr_med":2.33,"cr_p75":3.67,"qr_p25":1.61,"qr_med":2.24,"qr_p75":3.48,"cash_p25":1.16,"cash_med":1.46,"cash_p75":2.62},{"t":256703,"cr_p25":1.85,"cr_med":2.6,"cr_p75":3.45,"qr_p25":1.67,"qr_med":2.41,"qr_p75":3.24,"cash_p25":1.32,"cash_med":1.85,"cash_p75":2.59},{"t":256704,"cr_p25":1.83,"cr_med":2.49,"cr_p75":3.38,"qr_p25":1.69,"qr_med":2.35,"qr_p75":3.13,"cash_p25":1.16,"cash_med":1.87,"cash_p75":2.49},{"t":256705,"cr_p25":1.79,"cr_med":2.41,"cr_p75":3.36,"qr_p25":1.65,"qr_med":2.21,"qr_p75":3.13,"cash_p25":1.03,"cash_med":1.47,"cash_p75":2.37},{"t":256706,"cr_p25":1.65,"cr_med":2.51,"cr_p75":3.26,"qr_p25":1.49,"qr_med":2.35,"qr_p75":2.98,"cash_p25":0.98,"cash_med":1.38,"cash_p75":2.11},{"t":256707,"cr_p25":1.6,"cr_med":2.23,"cr_p75":3.39,"qr_p25":1.48,"qr_med":2.08,"qr_p75":3.07,"cash_p25":0.98,"cash_med":1.27,"cash_p75":2.18},{"t":256708,"cr_p25":1.48,"cr_med":2.27,"cr_p75":3.36,"qr_p25":1.22,"qr_med":2.16,"qr_p75":3.08,"cash_p25":0.75,"cash_med":1.04,"cash_p75":1.97},{"t":256709,"cr_p25":1.41,"cr_med":2.0,"cr_p75":3.22,"qr_p25":1.15,"qr_med":1.81,"qr_p75":2.86,"cash_p25":0.63,"cash_med":0.96,"cash_p75":1.72},{"t":256710,"cr_p25":1.55,"cr_med":2.05,"cr_p75":2.93,"qr_p25":1.4,"qr_med":1.9,"qr_p75":2.71,"cash_p25":0.83,"cash_med":1.18,"cash_p75":1.74},{"t":256711,"cr_p25":1.3,"cr_med":1.85,"cr_p75":2.9,"qr_p25":1.2,"qr_med":1.7,"qr_p75":2.65,"cash_p25":0.71,"cash_med":0.97,"cash_p75":1.69},{"t":256712,"cr_p25":1.23,"cr_med":1.5,"cr_p75":2.77,"qr_p25":1.1,"qr_med":1.41,"qr_p75":2.54,"cash_p25":0.67,"cash_med":0.95,"cash_p75":1.62},{"t":256801,"cr_p25":1.32,"cr_med":1.73,"cr_p75":2.79,"qr_p25":1.19,"qr_med":1.59,"qr_p75":2.62,"cash_p25":0.54,"cash_med":0.81,"cash_p75":1.31},{"t":256802,"cr_p25":1.28,"cr_med":1.6,"cr_p75":2.8,"qr_p25":1.17,"qr_med":1.48,"qr_p75":2.5,"cash_p25":0.7,"cash_med":0.93,"cash_p75":1.61},{"t":256803,"cr_p25":1.41,"cr_med":1.79,"cr_p75":2.99,"qr_p25":1.31,"qr_med":1.65,"qr_p75":2.75,"cash_p25":0.8,"cash_med":1.12,"cash_p75":1.96},{"t":256804,"cr_p25":1.36,"cr_med":1.66,"cr_p75":2.98,"qr_p25":1.25,"qr_med":1.52,"qr_p75":2.76,"cash_p25":0.8,"cash_med":0.99,"cash_p75":1.83},{"t":256805,"cr_p25":1.41,"cr_med":1.84,"cr_p75":2.8,"qr_p25":1.31,"qr_med":1.69,"qr_p75":2.6,"cash_p25":0.93,"cash_med":1.12,"cash_p75":1.88},{"t":256806,"cr_p25":1.27,"cr_med":1.76,"cr_p75":3.0,"qr_p25":1.18,"qr_med":1.6,"qr_p75":2.76,"cash_p25":0.83,"cash_med":1.18,"cash_p75":1.95},{"t":256807,"cr_p25":1.22,"cr_med":1.88,"cr_p75":2.64,"qr_p25":1.15,"qr_med":1.69,"qr_p75":2.45,"cash_p25":0.73,"cash_med":1.02,"cash_p75":1.81},{"t":256808,"cr_p25":1.24,"cr_med":1.98,"cr_p75":2.92,"qr_p25":1.16,"qr_med":1.79,"qr_p75":2.77,"cash_p25":0.7,"cash_med":1.04,"cash_p75":1.97},{"t":256809,"cr_p25":1.23,"cr_med":1.72,"cr_p75":3.06,"qr_p25":1.07,"qr_med":1.46,"qr_p75":2.87,"cash_p25":0.58,"cash_med":0.77,"cash_p75":1.77},{"t":256810,"cr_p25":1.1,"cr_med":1.37,"cr_p75":2.95,"qr_p25":0.97,"qr_med":1.21,"qr_p75":2.78,"cash_p25":0.44,"cash_med":0.65,"cash_p75":1.44},{"t":256811,"cr_p25":1.07,"cr_med":1.17,"cr_p75":2.54,"qr_p25":0.92,"qr_med":1.06,"qr_p75":2.32,"cash_p25":0.38,"cash_med":0.54,"cash_p75":1.33},{"t":256812,"cr_p25":0.97,"cr_med":1.12,"cr_p75":2.33,"qr_p25":0.82,"qr_med":1.06,"qr_p75":2.17,"cash_p25":0.37,"cash_med":0.49,"cash_p75":1.17},{"t":256901,"cr_p25":1.2,"cr_med":1.36,"cr_p75":2.42,"qr_p25":1.14,"qr_med":1.27,"qr_p75":2.32,"cash_p25":0.65,"cash_med":0.85,"cash_p75":1.51},{"t":256902,"cr_p25":1.27,"cr_med":1.62,"cr_p75":2.36,"qr_p25":1.15,"qr_med":1.5,"qr_p75":2.25,"cash_p25":0.65,"cash_med":0.93,"cash_p75":1.49},{"t":256903,"cr_p25":1.15,"cr_med":1.43,"cr_p75":2.21,"qr_p25":1.08,"qr_med":1.31,"qr_p75":2.06,"cash_p25":0.62,"cash_med":0.84,"cash_p75":1.38},{"t":256904,"cr_p25":1.08,"cr_med":1.34,"cr_p75":2.3,"qr_p25":0.97,"qr_med":1.24,"qr_p75":2.13,"cash_p25":0.51,"cash_med":0.73,"cash_p75":1.18},{"t":256905,"cr_p25":1.17,"cr_med":1.46,"cr_p75":1.99,"qr_p25":1.02,"qr_med":1.37,"qr_p75":1.8,"cash_p25":0.62,"cash_med":0.95,"cash_p75":1.26},{"t":256906,"cr_p25":1.38,"cr_med":1.61,"cr_p75":2.05,"qr_p25":1.26,"qr_med":1.5,"qr_p75":1.87,"cash_p25":0.77,"cash_med":1.09,"cash_p75":1.32},{"t":256907,"cr_p25":1.28,"cr_med":1.62,"cr_p75":1.95,"qr_p25":1.17,"qr_med":1.5,"qr_p75":1.77,"cash_p25":0.72,"cash_med":0.95,"cash_p75":1.29},{"t":256908,"cr_p25":1.17,"cr_med":1.53,"cr_p75":1.99,"qr_p25":1.08,"qr_med":1.36,"qr_p75":1.76,"cash_p25":0.56,"cash_med":0.84,"cash_p75":1.19}],"level":[{"t":256609,"cr_p25":2.04,"cr_med":2.75,"cr_p75":3.86,"qr_p25":1.9,"qr_med":2.56,"qr_p75":3.68,"cash_p25":1.4,"cash_med":1.99,"cash_p75":3.09},{"t":256610,"cr_p25":1.77,"cr_med":2.5,"cr_p75":3.32,"qr_p25":1.61,"qr_med":2.39,"qr_p75":3.15,"cash_p25":1.13,"cash_med":1.68,"cash_p75":2.49},{"t":256611,"cr_p25":1.51,"cr_med":2.4,"cr_p75":3.19,"qr_p25":1.35,"qr_med":2.22,"qr_p75":3.0,"cash_p25":0.96,"cash_med":1.49,"cash_p75":2.33},{"t":256612,"cr_p25":1.48,"cr_med":2.25,"cr_p75":3.44,"qr_p25":1.34,"qr_med":2.13,"qr_p75":3.3,"cash_p25":0.87,"cash_med":1.58,"cash_p75":2.38},{"t":256701,"cr_p25":1.73,"cr_med":2.45,"cr_p75":3.49,"qr_p25":1.59,"qr_med":2.3,"qr_p75":3.33,"cash_p25":1.12,"cash_med":1.67,"cash_p75":2.39},{"t":256702,"cr_p25":1.69,"cr_med":2.56,"cr_p75":3.69,"qr_p25":1.56,"qr_med":2.46,"qr_p75":3.57,"cash_p25":1.1,"cash_med":1.79,"cash_p75":2.63},{"t":256703,"cr_p25":1.87,"cr_med":2.62,"cr_p75":3.63,"qr_p25":1.68,"qr_med":2.44,"qr_p75":3.43,"cash_p25":1.27,"cash_med":2.0,"cash_p75":2.65},{"t":256704,"cr_p25":1.79,"cr_med":2.53,"cr_p75":3.68,"qr_p25":1.66,"qr_med":2.37,"qr_p75":3.49,"cash_p25":1.09,"cash_med":1.87,"cash_p75":2.77},{"t":256705,"cr_p25":1.73,"cr_med":2.34,"cr_p75":3.35,"qr_p25":1.54,"qr_med":2.19,"qr_p75":3.19,"cash_p25":0.96,"cash_med":1.61,"cash_p75":2.39},{"t":256706,"cr_p25":1.56,"cr_med":2.48,"cr_p75":3.34,"qr_p25":1.44,"qr_med":2.25,"qr_p75":3.14,"cash_p25":0.88,"cash_med":1.6,"cash_p75":2.13},{"t":256707,"cr_p25":1.55,"cr_med":2.21,"cr_p75":3.37,"qr_p25":1.46,"qr_med":2.09,"qr_p75":3.08,"cash_p25":0.85,"cash_med":1.52,"cash_p75":2.15},{"t":256708,"cr_p25":1.42,"cr_med":2.29,"cr_p75":3.19,"qr_p25":1.18,"qr_med":2.12,"qr_p75":2.98,"cash_p25":0.66,"cash_med":1.33,"cash_p75":1.96},{"t":256709,"cr_p25":1.32,"cr_med":1.96,"cr_p75":3.12,"qr_p25":1.09,"qr_med":1.81,"qr_p75":2.83,"cash_p25":0.54,"cash_med":1.03,"cash_p75":1.6},{"t":256710,"cr_p25":1.36,"cr_med":1.95,"cr_p75":2.7,"qr_p25":1.27,"qr_med":1.75,"qr_p75":2.55,"cash_p25":0.82,"cash_med":1.18,"cash_p75":1.71},{"t":256711,"cr_p25":1.26,"cr_med":1.73,"cr_p75":2.51,"qr_p25":1.11,"qr_med":1.6,"qr_p75":2.35,"cash_p25":0.69,"cash_med":0.98,"cash_p75":1.54},{"t":256712,"cr_p25":1.15,"cr_med":1.52,"cr_p75":2.53,"qr_p25":1.05,"qr_med":1.42,"qr_p75":2.35,"cash_p25":0.59,"cash_med":0.97,"cash_p75":1.6},{"t":256801,"cr_p25":1.29,"cr_med":1.65,"cr_p75":2.79,"qr_p25":1.19,"qr_med":1.54,"qr_p75":2.55,"cash_p25":0.53,"cash_med":0.88,"cash_p75":1.42},{"t":256802,"cr_p25":1.16,"cr_med":1.71,"cr_p75":2.84,"qr_p25":1.06,"qr_med":1.52,"qr_p75":2.63,"cash_p25":0.66,"cash_med":0.94,"cash_p75":1.9},{"t":256803,"cr_p25":1.36,"cr_med":1.83,"cr_p75":3.0,"qr_p25":1.27,"qr_med":1.71,"qr_p75":2.74,"cash_p25":0.82,"cash_med":1.19,"cash_p75":2.03},{"t":256804,"cr_p25":1.26,"cr_med":1.79,"cr_p75":2.95,"qr_p25":1.17,"qr_med":1.67,"qr_p75":2.6,"cash_p25":0.78,"cash_med":1.04,"cash_p75":2.01},{"t":256805,"cr_p25":1.37,"cr_med":1.88,"cr_p75":2.79,"qr_p25":1.28,"qr_med":1.73,"qr_p75":2.61,"cash_p25":0.91,"cash_med":1.27,"cash_p75":1.89},{"t":256806,"cr_p25":1.28,"cr_med":1.83,"cr_p75":2.65,"qr_p25":1.19,"qr_med":1.68,"qr_p75":2.51,"cash_p25":0.82,"cash_med":1.19,"cash_p75":1.88},{"t":256807,"cr_p25":1.19,"cr_med":1.6,"cr_p75":2.48,"qr_p25":1.1,"qr_med":1.43,"qr_p75":2.29,"cash_p25":0.7,"cash_med":0.98,"cash_p75":1.67},{"t":256808,"cr_p25":1.19,"cr_med":1.52,"cr_p75":2.43,"qr_p25":1.09,"qr_med":1.36,"qr_p75":2.18,"cash_p25":0.68,"cash_med":0.96,"cash_p75":1.66},{"t":256809,"cr_p25":1.0,"cr_med":1.36,"cr_p75":2.18,"qr_p25":0.93,"qr_med":1.25,"qr_p75":2.05,"cash_p25":0.55,"cash_med":0.8,"cash_p75":1.46},{"t":256810,"cr_p25":1.0,"cr_med":1.21,"cr_p75":2.0,"qr_p25":0.89,"qr_med":1.12,"qr_p75":1.86,"cash_p25":0.44,"cash_med":0.67,"cash_p75":1.25},{"t":256811,"cr_p25":0.98,"cr_med":1.15,"cr_p75":1.82,"qr_p25":0.84,"qr_med":1.02,"qr_p75":1.66,"cash_p25":0.38,"cash_med":0.55,"cash_p75":1.02},{"t":256812,"cr_p25":0.9,"cr_med":1.12,"cr_p75":1.46,"qr_p25":0.8,"qr_med":1.03,"qr_p75":1.32,"cash_p25":0.36,"cash_med":0.47,"cash_p75":0.76},{"t":256901,"cr_p25":1.16,"cr_med":1.44,"cr_p75":1.94,"qr_p25":1.09,"qr_med":1.38,"qr_p75":1.82,"cash_p25":0.71,"cash_med":0.96,"cash_p75":1.21},{"t":256902,"cr_p25":1.28,"cr_med":1.6,"cr_p75":2.04,"qr_p25":1.17,"qr_med":1.48,"qr_p75":1.89,"cash_p25":0.69,"cash_med":0.98,"cash_p75":1.31},{"t":256903,"cr_p25":1.22,"cr_med":1.49,"cr_p75":2.06,"qr_p25":1.12,"qr_med":1.37,"qr_p75":1.85,"cash_p25":0.68,"cash_med":0.89,"cash_p75":1.3},{"t":256904,"cr_p25":1.12,"cr_med":1.38,"cr_p75":2.03,"qr_p25":1.0,"qr_med":1.25,"qr_p75":1.84,"cash_p25":0.56,"cash_med":0.76,"cash_p75":1.17},{"t":256905,"cr_p25":1.17,"cr_med":1.49,"cr_p75":1.99,"qr_p25":1.06,"qr_med":1.36,"qr_p75":1.85,"cash_p25":0.69,"cash_med":0.95,"cash_p75":1.28},{"t":256906,"cr_p25":1.4,"cr_med":1.77,"cr_p75":2.34,"qr_p25":1.3,"qr_med":1.62,"qr_p75":2.16,"cash_p25":0.81,"cash_med":1.12,"cash_p75":1.64},{"t":256907,"cr_p25":1.3,"cr_med":1.6,"cr_p75":2.22,"qr_p25":1.2,"qr_med":1.5,"qr_p75":2.0,"cash_p25":0.73,"cash_med":0.99,"cash_p75":1.41},{"t":256908,"cr_p25":1.16,"cr_med":1.54,"cr_p75":2.06,"qr_p25":1.04,"qr_med":1.38,"qr_p75":1.88,"cash_p25":0.58,"cash_med":0.91,"cash_p75":1.21}],"prov":[{"t":256609,"cr_p25":1.5,"cr_med":2.14,"cr_p75":3.95,"qr_p25":1.38,"qr_med":2.01,"qr_p75":3.7,"cash_p25":0.78,"cash_med":1.37,"cash_p75":2.51},{"t":256610,"cr_p25":1.49,"cr_med":2.13,"cr_p75":3.83,"qr_p25":1.41,"qr_med":1.89,"qr_p75":3.59,"cash_p25":0.67,"cash_med":1.19,"cash_p75":2.27},{"t":256611,"cr_p25":1.38,"cr_med":1.98,"cr_p75":3.35,"qr_p25":1.29,"qr_med":1.78,"qr_p75":3.16,"cash_p25":0.65,"cash_med":1.03,"cash_p75":1.88},{"t":256612,"cr_p25":1.24,"cr_med":1.84,"cr_p75":3.3,"qr_p25":1.16,"qr_med":1.71,"qr_p75":3.02,"cash_p25":0.64,"cash_med":0.94,"cash_p75":2.11},{"t":256701,"cr_p25":1.42,"cr_med":2.02,"cr_p75":3.38,"qr_p25":1.33,"qr_med":1.88,"qr_p75":3.18,"cash_p25":0.68,"cash_med":1.12,"cash_p75":2.42},{"t":256702,"cr_p25":1.39,"cr_med":1.88,"cr_p75":3.36,"qr_p25":1.28,"qr_med":1.73,"qr_p75":3.15,"cash_p25":0.77,"cash_med":1.1,"cash_p75":2.6},{"t":256703,"cr_p25":1.35,"cr_med":1.88,"cr_p75":3.75,"qr_p25":1.25,"qr_med":1.67,"qr_p75":3.57,"cash_p25":0.81,"cash_med":1.23,"cash_p75":2.33},{"t":256704,"cr_p25":1.26,"cr_med":1.87,"cr_p75":3.14,"qr_p25":1.16,"qr_med":1.7,"qr_p75":2.89,"cash_p25":0.7,"cash_med":1.08,"cash_p75":1.88},{"t":256705,"cr_p25":1.16,"cr_med":1.73,"cr_p75":2.93,"qr_p25":1.1,"qr_med":1.59,"qr_p75":2.7,"cash_p25":0.58,"cash_med":0.95,"cash_p75":1.59},{"t":256706,"cr_p25":1.2,"cr_med":1.65,"cr_p75":2.97,"qr_p25":1.11,"qr_med":1.51,"qr_p75":2.74,"cash_p25":0.57,"cash_med":0.88,"cash_p75":1.74},{"t":256707,"cr_p25":1.14,"cr_med":1.62,"cr_p75":3.0,"qr_p25":1.05,"qr_med":1.52,"qr_p75":2.8,"cash_p25":0.56,"cash_med":1.01,"cash_p75":1.94},{"t":256708,"cr_p25":1.08,"cr_med":1.54,"cr_p75":3.13,"qr_p25":0.99,"qr_med":1.31,"qr_p75":2.55,"cash_p25":0.52,"cash_med":0.81,"cash_p75":1.55},{"t":256709,"cr_p25":1.04,"cr_med":1.54,"cr_p75":2.35,"qr_p25":0.94,"qr_med":1.28,"qr_p75":2.18,"cash_p25":0.44,"cash_med":0.66,"cash_p75":1.21},{"t":256710,"cr_p25":1.19,"cr_med":1.71,"cr_p75":2.32,"qr_p25":1.1,"qr_med":1.52,"qr_p75":2.19,"cash_p25":0.66,"cash_med":0.82,"cash_p75":1.5},{"t":256711,"cr_p25":1.13,"cr_med":1.45,"cr_p75":2.24,"qr_p25":1.02,"qr_med":1.33,"qr_p75":2.12,"cash_p25":0.54,"cash_med":0.73,"cash_p75":1.22},{"t":256712,"cr_p25":1.11,"cr_med":1.4,"cr_p75":2.34,"qr_p25":1.03,"qr_med":1.32,"qr_p75":2.2,"cash_p25":0.5,"cash_med":0.67,"cash_p75":1.05},{"t":256801,"cr_p25":1.11,"cr_med":1.56,"cr_p75":2.29,"qr_p25":1.03,"qr_med":1.44,"qr_p75":2.11,"cash_p25":0.44,"cash_med":0.63,"cash_p75":1.04},{"t":256802,"cr_p25":1.15,"cr_med":1.46,"cr_p75":2.56,"qr_p25":1.04,"qr_med":1.37,"qr_p75":2.32,"cash_p25":0.5,"cash_med":0.75,"cash_p75":1.03},{"t":256803,"cr_p25":1.22,"cr_med":1.66,"cr_p75":2.59,"qr_p25":1.11,"qr_med":1.59,"qr_p75":2.35,"cash_p25":0.61,"cash_med":0.92,"cash_p75":1.55},{"t":256804,"cr_p25":1.12,"cr_med":1.69,"cr_p75":2.34,"qr_p25":1.0,"qr_med":1.55,"qr_p75":2.11,"cash_p25":0.54,"cash_med":0.79,"cash_p75":1.26},{"t":256805,"cr_p25":1.32,"cr_med":1.65,"cr_p75":2.57,"qr_p25":1.24,"qr_med":1.52,"qr_p75":2.37,"cash_p25":0.6,"cash_med":1.06,"cash_p75":1.47},{"t":256806,"cr_p25":1.19,"cr_med":1.63,"cr_p75":2.47,"qr_p25":1.11,"qr_med":1.53,"qr_p75":2.25,"cash_p25":0.55,"cash_med":0.95,"cash_p75":1.54},{"t":256807,"cr_p25":1.14,"cr_med":1.44,"cr_p75":2.29,"qr_p25":1.05,"qr_med":1.34,"qr_p75":2.22,"cash_p25":0.56,"cash_med":0.81,"cash_p75":1.39},{"t":256808,"cr_p25":1.21,"cr_med":1.46,"cr_p75":2.28,"qr_p25":1.11,"qr_med":1.34,"qr_p75":2.16,"cash_p25":0.54,"cash_med":0.76,"cash_p75":1.35},{"t":256809,"cr_p25":1.22,"cr_med":1.35,"cr_p75":2.2,"qr_p25":1.12,"qr_med":1.28,"qr_p75":2.06,"cash_p25":0.5,"cash_med":0.72,"cash_p75":1.24},{"t":256810,"cr_p25":1.1,"cr_med":1.25,"cr_p75":2.3,"qr_p25":0.99,"qr_med":1.19,"qr_p75":2.1,"cash_p25":0.43,"cash_med":0.67,"cash_p75":1.12},{"t":256811,"cr_p25":1.09,"cr_med":1.16,"cr_p75":2.01,"qr_p25":0.98,"qr_med":1.09,"qr_p75":1.88,"cash_p25":0.36,"cash_med":0.52,"cash_p75":0.86},{"t":256812,"cr_p25":0.93,"cr_med":1.12,"cr_p75":1.71,"qr_p25":0.84,"qr_med":1.05,"qr_p75":1.59,"cash_p25":0.3,"cash_med":0.4,"cash_p75":0.62},{"t":256901,"cr_p25":1.12,"cr_med":1.33,"cr_p75":1.95,"qr_p25":1.05,"qr_med":1.27,"qr_p75":1.84,"cash_p25":0.46,"cash_med":0.71,"cash_p75":0.92},{"t":256902,"cr_p25":1.11,"cr_med":1.3,"cr_p75":2.03,"qr_p25":1.02,"qr_med":1.23,"qr_p75":1.87,"cash_p25":0.43,"cash_med":0.71,"cash_p75":0.98},{"t":256903,"cr_p25":1.04,"cr_med":1.33,"cr_p75":2.01,"qr_p25":0.99,"qr_med":1.24,"qr_p75":1.8,"cash_p25":0.42,"cash_med":0.68,"cash_p75":0.99},{"t":256904,"cr_p25":0.96,"cr_med":1.27,"cr_p75":1.87,"qr_p25":0.9,"qr_med":1.2,"qr_p75":1.65,"cash_p25":0.37,"cash_med":0.56,"cash_p75":0.87},{"t":256905,"cr_p25":1.02,"cr_med":1.33,"cr_p75":1.77,"qr_p25":0.95,"qr_med":1.26,"qr_p75":1.65,"cash_p25":0.44,"cash_med":0.63,"cash_p75":0.99},{"t":256906,"cr_p25":1.11,"cr_med":1.46,"cr_p75":2.03,"qr_p25":1.05,"qr_med":1.37,"qr_p75":1.86,"cash_p25":0.5,"cash_med":0.7,"cash_p75":1.23},{"t":256907,"cr_p25":1.04,"cr_med":1.45,"cr_p75":1.98,"qr_p25":0.99,"qr_med":1.36,"qr_p75":1.77,"cash_p25":0.45,"cash_med":0.69,"cash_p75":1.11},{"t":256908,"cr_p25":0.96,"cr_med":1.39,"cr_p75":1.97,"qr_p25":0.9,"qr_med":1.29,"qr_p75":1.72,"cash_p25":0.4,"cash_med":0.58,"cash_p75":1.03}]},"decomp":{"mom":{"baseT":256907,"cr":{"total":0.2001,"fromNumerator":-0.1227,"fromDenominator":0.3356},"qr":{"total":0.1493,"fromNumerator":-0.1478,"fromDenominator":0.3124},"cash":{"total":0.0385,"fromNumerator":-0.2019,"fromDenominator":0.2614}},"yoy":{"baseT":256808,"cr":{"total":0.0998,"fromNumerator":-0.0865,"fromDenominator":0.1913},"qr":{"total":0.031,"fromNumerator":-0.1404,"fromDenominator":0.1795},"cash":{"total":0.0041,"fromNumerator":-0.1346,"fromDenominator":0.1465}}},"waterfall":{"mom":{"baseT":256907,"ca":[{"name":"เงินฝากและรายการเทียบเท่าเงินสดอื่น","value":54020001.0,"delta":-5199892.0},{"name":"ลูกหนี้หมุนเวียนและรายได้ค้างรับอื่น","value":13247089.0,"delta":1317999.0},{"name":"สินค้าและวัสดุคงเหลือ","value":5775479.0,"delta":586233.0},{"name":"เงินฝากธนาคารพาณิชย์เพื่อรับจ่ายเงินกับคลัง","value":427718.0,"delta":422918.0},{"name":"ลูกหนี้เงินยืม","value":4080.0,"delta":-34960.0},{"name":"สินทรัพย์หมุนเวียนอื่น","value":83213.0,"delta":6657.0},{"name":"ค่าเผื่อหนี้สงสัยจะสูญ ค่าขายสินค้าและบริการ","value":-353869.0,"delta":-2509.0},{"name":"เงินฝากคลัง","value":248712.0,"delta":0.0}],"cl":[{"name":"เงินรับฝากทั่วไป","value":4822279.0,"delta":-3160212.0},{"name":"เจ้าหนี้อื่น  เงินนอกงบประมาณฝากธนาคารพาณิชย์","value":12428663.0,"delta":1710888.0},{"name":"ค่าใช้จ่ายค้างจ่ายอื่น ","value":3410136.0,"delta":-630659.0},{"name":"รายได้รับล่วงหน้า","value":521552.0,"delta":-148558.0},{"name":"เงินประกัน","value":248712.0,"delta":0.0}]},"yoy":{"baseT":256808,"ca":[{"name":"เงินฝากและรายการเทียบเท่าเงินสดอื่น","value":54020001.0,"delta":-3462240.0},{"name":"สินค้าและวัสดุคงเหลือ","value":5775479.0,"delta":1258217.0},{"name":"เงินฝากธนาคารพาณิชย์เพื่อรับจ่ายเงินกับคลัง","value":427718.0,"delta":427718.0},{"name":"ลูกหนี้เงินยืม","value":4080.0,"delta":-253229.0},{"name":"ลูกหนี้หมุนเวียนและรายได้ค้างรับอื่น","value":13247089.0,"delta":163035.0},{"name":"ค่าเผื่อหนี้สงสัยจะสูญ ค่าขายสินค้าและบริการ","value":-353869.0,"delta":-41434.0},{"name":"สินทรัพย์หมุนเวียนอื่น","value":83213.0,"delta":-36774.0},{"name":"เงินฝากคลัง","value":248712.0,"delta":-16124.0}],"cl":[{"name":"เงินรับฝากทั่วไป","value":4822279.0,"delta":-1493218.0},{"name":"รายได้รับล่วงหน้า","value":521552.0,"delta":-1054935.0},{"name":"ค่าใช้จ่ายค้างจ่ายอื่น ","value":3410136.0,"delta":739397.0},{"name":"เจ้าหนี้อื่น  เงินนอกงบประมาณฝากธนาคารพาณิชย์","value":12428663.0,"delta":593006.0},{"name":"เงินประกัน","value":248712.0,"delta":-16124.0}]}},"topAccounts":{"mom":{"baseT":256907,"accounts":[{"acc":"1101030102.102","name":"เงินฝากธนาคาร - นอกงบประมาณรอการจัดสรรออมทรัพย์","cls":"CA","value":5611433.0,"delta":-3236151.0},{"acc":"2111020199.205","name":"เงินรับฝากกองทุน UC - Fixed Cost","cls":"CL","value":597054.0,"delta":-2035047.0},{"acc":"1101030102.101","name":"เงินฝากธนาคาร - นอกงบประมาณ ออมทรัพย์","cls":"CA","value":48408568.0,"delta":-1963741.0},{"acc":"2102040110.111","name":"ค่าตอบแทนการปฏิบัติงานในลักษณะเบี้ยเลี้ยงเหมาจ่ายค้างจ่าย","cls":"CL","value":1645582.0,"delta":-1322218.0},{"acc":"2111020199.206","name":"เงินรับฝากกองทุน UC -นอกเหนือ Fixed  Cost","cls":"CL","value":50750.0,"delta":-819000.0},{"acc":"1102050101.202","name":"ลูกหนี้ค่ารักษา UC - IP ","cls":"CA","value":2712236.0,"delta":743374.0},{"acc":"2101020199.136","name":"เจ้าหนี้ - วัสดุวิทยาศาสตร์และการแพทย์","cls":"CL","value":1536394.0,"delta":454531.0},{"acc":"2101020199.134","name":"เจ้าหนี้ - ยา","cls":"CL","value":5385679.0,"delta":441669.0},{"acc":"1101020603.101","name":"เงินฝากธนาคาร -  ในงบประมาณ","cls":"CA","value":427718.0,"delta":422918.0},{"acc":"2102040199.105","name":"ใบสำคัญค้างจ่าย","cls":"CL","value":427718.0,"delta":422918.0},{"acc":"1102050101.401","name":"ลูกหนี้ค่ารักษา-เบิกจ่ายตรงกรมบัญชีกลาง OP","cls":"CA","value":1571915.0,"delta":310774.0},{"acc":"2101020199.137","name":"เจ้าหนี้ - วัสดุอื่น","cls":"CL","value":574008.0,"delta":306124.0},{"acc":"1105010103.104","name":"วัสดุการแพทย์ทั่วไป","cls":"CA","value":1125774.0,"delta":299896.0},{"acc":"2101020199.202","name":"เจ้าหนี้ค่ารักษา OP-UC นอก CUP (ในจังหวัดสังกัด สธ.)","cls":"CL","value":1032981.0,"delta":275325.0},{"acc":"2102040110.113","name":"ค่าสาธารณูปโภคค้างจ่าย","cls":"CL","value":243350.0,"delta":229661.0},{"acc":"2111020199.204","name":"เงินรับฝากกองทุน UC วัสดุ","cls":"CL","value":813289.0,"delta":-206569.0},{"acc":"1105010103.105","name":"วัสดุวิทยาศาสตร์และการแพทย์","cls":"CA","value":676167.0,"delta":178598.0},{"acc":"2103010103.502","name":"รายได้ค่ารักษาแรงงานต่างด้าวรับล่วงหน้า","cls":"CL","value":521552.0,"delta":-148558.0},{"acc":"2101020199.139","name":"เจ้าหนี้ - ครุภัณฑ์","cls":"CL","value":233950.0,"delta":131360.0},{"acc":"2101020199.138","name":"เจ้าหนี้ - อื่น","cls":"CL","value":464367.0,"delta":130377.0}]},"yoy":{"baseT":256808,"accounts":[{"acc":"2111020199.206","name":"เงินรับฝากกองทุน UC -นอกเหนือ Fixed  Cost","cls":"CL","value":50750.0,"delta":-3924079.0},{"acc":"2111020199.201","name":"เงินรับฝากกองทุน UC ","cls":"CL","value":3125922.0,"delta":2522616.0},{"acc":"1101030102.102","name":"เงินฝากธนาคาร - นอกงบประมาณรอการจัดสรรออมทรัพย์","cls":"CA","value":5611433.0,"delta":-2281287.0},{"acc":"2101020199.134","name":"เจ้าหนี้ - ยา","cls":"CL","value":5385679.0,"delta":-1948514.0},{"acc":"1101030102.101","name":"เงินฝากธนาคาร - นอกงบประมาณ ออมทรัพย์","cls":"CA","value":48408568.0,"delta":-1180953.0},{"acc":"2103010103.502","name":"รายได้ค่ารักษาแรงงานต่างด้าวรับล่วงหน้า","cls":"CL","value":521552.0,"delta":-1054935.0},{"acc":"2101020199.136","name":"เจ้าหนี้ - วัสดุวิทยาศาสตร์และการแพทย์","cls":"CL","value":1536394.0,"delta":851320.0},{"acc":"2101020199.135","name":"เจ้าหนี้ - วัสดุการแพทย์ทั่วไป","cls":"CL","value":2466705.0,"delta":733674.0},{"acc":"2101020199.202","name":"เจ้าหนี้ค่ารักษา OP-UC นอก CUP (ในจังหวัดสังกัด สธ.)","cls":"CL","value":1032981.0,"delta":725323.0},{"acc":"1105010103.104","name":"วัสดุการแพทย์ทั่วไป","cls":"CA","value":1125774.0,"delta":576157.0},{"acc":"1102050101.401","name":"ลูกหนี้ค่ารักษา-เบิกจ่ายตรงกรมบัญชีกลาง OP","cls":"CA","value":1571915.0,"delta":467852.0},{"acc":"2102040110.111","name":"ค่าตอบแทนการปฏิบัติงานในลักษณะเบี้ยเลี้ยงเหมาจ่ายค้างจ่าย","cls":"CL","value":1645582.0,"delta":436682.0},{"acc":"1102050101.402","name":"ลูกหนี้ค่ารักษา - เบิกจ่ายตรงกรมบัญชีกลาง IP","cls":"CA","value":702892.0,"delta":-435978.0},{"acc":"1101020603.101","name":"เงินฝากธนาคาร -  ในงบประมาณ","cls":"CA","value":427718.0,"delta":427718.0},{"acc":"2102040199.105","name":"ใบสำคัญค้างจ่าย","cls":"CL","value":427718.0,"delta":427718.0},{"acc":"1105010103.105","name":"วัสดุวิทยาศาสตร์และการแพทย์","cls":"CA","value":676167.0,"delta":403320.0},{"acc":"1102050101.216","name":"ลูกหนี้ค่ารักษา UC - OP บริการเฉพาะ (CR)","cls":"CA","value":688980.0,"delta":-358915.0},{"acc":"1102050101.202","name":"ลูกหนี้ค่ารักษา UC - IP ","cls":"CA","value":2712236.0,"delta":-324755.0},{"acc":"1102050102.801","name":"ลูกหนี้ค่ารักษา - เบิกจ่ายตรง อปท. OP","cls":"CA","value":1049912.0,"delta":319956.0},{"acc":"2101020199.148","name":"เจ้าหนี้ - ค่าตรวจเอกซเรย์ (X-Ray)","cls":"CL","value":188090.0,"delta":-279195.0}]}}}